{"assets":[],"ddd":0,"fr":60,"h":144,"ip":0,"layers":[{"ddd":0,"ind":1,"ty":4,"nm":"Layer 1","hd":false,"sr":1,"ks":{"a":{"a":0,"k":[0,-0.094]},"o":{"a":0,"k":100},"p":{"a":0,"k":[23,21.906]},"r":{"a":0,"k":0},"s":{"a":0,"k":[100,100]},"sk":{"a":0,"k":0},"sa":{"a":0,"k":0}},"ao":0,"ip":0,"op":121,"st":0,"bm":0,"shapes":[{"ty":"gr","hd":false,"nm":"Path 1 Group","bm":0,"it":[{"ty":"sh","hd":false,"nm":"Path 1","d":1,"ks":{"a":0,"k":{"c":false,"i":[[0,0],[0,0],[10.185,0.263],[0,0],[-6.392,-1.967]],"o":[[0,0],[-12.685,-3.825],[0,0],[15.008,0.13],[0,0]],"v":[[172.25,90.406],[169.25,58.906],[134.75,53.181],[138.25,85.844],[172.25,90.406]]}}},{"ty":"fl","hd":false,"bm":0,"c":{"a":0,"k":[1,0.667,0]},"r":1,"o":{"a":0,"k":100}},{"ty":"tr","nm":"Transform","a":{"a":0,"k":[0,0]},"o":{"a":0,"k":100},"p":{"a":1,"k":[{"t":0,"s":[0,0],"i":{"x":0.15,"y":1.35},"o":{"x":0.15,"y":0.45},"ti":[0,0],"to":[0,0]},{"t":60,"s":[6,0.435],"i":{"x":0.15,"y":1.35},"o":{"x":0.15,"y":0.45},"ti":[0,0],"to":[0,0]},{"t":120,"s":[0,0],"i":{"x":0,"y":0},"o":{"x":1,"y":1}}]},"r":{"a":0,"k":0},"s":{"a":0,"k":[100,100]},"sk":{"a":0,"k":0},"sa":{"a":0,"k":0}}],"np":0},{"ty":"gr","hd":false,"nm":"Path 1 Group","bm":0,"it":[{"ty":"sh","hd":false,"nm":"Path 1","d":1,"ks":{"a":0,"k":{"c":false,"i":[[0,0],[0,0],[-9.352,0.183],[0,0],[6.795,-2.719]],"o":[[0,0],[10.031,-2.723],[0,0],[-13.218,0.119],[0,0]],"v":[[100.25,58.406],[104.75,89.906],[134.25,85.865],[130.75,53.147],[100.25,58.407]]}}},{"ty":"fl","hd":false,"bm":0,"c":{"a":0,"k":[0.784,0.784,0.933]},"r":1,"o":{"a":0,"k":100}},{"ty":"tr","nm":"Transform","a":{"a":0,"k":[0,0]},"o":{"a":0,"k":100},"p":{"a":1,"k":[{"t":0,"s":[0,0],"i":{"x":0.15,"y":1.35},"o":{"x":0.15,"y":0.45},"ti":[0,0],"to":[0,0]},{"t":60,"s":[-3.5,-0.527],"i":{"x":0.15,"y":1.35},"o":{"x":0.15,"y":0.45},"ti":[0,0],"to":[0,0]},{"t":120,"s":[0,0],"i":{"x":0,"y":0},"o":{"x":1,"y":1}}]},"r":{"a":0,"k":0},"s":{"a":0,"k":[100,100]},"sk":{"a":0,"k":0},"sa":{"a":0,"k":0}}],"np":0},{"ty":"gr","hd":false,"nm":"Path 1 Group","bm":0,"it":[{"ty":"sh","hd":false,"nm":"Path 1","d":1,"ks":{"a":0,"k":{"c":true,"i":[[0,0],[11.833,-3.833],[0,0],[-14.167,-4]],"o":[[-28,-9.2],[0,0],[22.4,-9.6],[0,0]],"v":[[88.25,43.906],[17.75,43.906],[23.25,90.406],[93.75,90.406]]}}},{"ty":"fl","hd":false,"bm":0,"c":{"a":0,"k":[0.89,0.373,0]},"r":1,"o":{"a":0,"k":100}},{"ty":"tr","nm":"Transform","a":{"a":0,"k":[0,0]},"o":{"a":0,"k":100},"p":{"a":1,"k":[{"t":0,"s":[0,0],"i":{"x":0.15,"y":1.35},"o":{"x":0.15,"y":0.45},"ti":[0,0],"to":[0,0]},{"t":60,"s":[-3,1.453],"i":{"x":0.15,"y":1.35},"o":{"x":0.15,"y":0.45},"ti":[0,0],"to":[0,0]},{"t":120,"s":[0.016,-0.001],"i":{"x":0,"y":0},"o":{"x":1,"y":1}}]},"r":{"a":0,"k":0},"s":{"a":0,"k":[100,100]},"sk":{"a":0,"k":0},"sa":{"a":0,"k":0}}],"np":0},{"ty":"gr","hd":false,"nm":"Path 1 Group","bm":0,"it":[{"ty":"sh","hd":false,"nm":"Path 1","d":1,"ks":{"a":0,"k":{"c":false,"i":[[0,0],[0,0],[7.231,0.743],[0,0],[-4.472,-2.017]],"o":[[0,0],[-7.528,-2.576],[0,0],[7.724,1.25],[0,0]],"v":[[166.25,30.644],[167.761,54.406],[145.451,49.589],[147.458,25.487],[166.25,30.644]]}}},{"ty":"fl","hd":false,"bm":0,"c":{"a":0,"k":[0.784,0.784,0.933]},"r":1,"o":{"a":0,"k":100}},{"ty":"tr","nm":"Transform","a":{"a":0,"k":[0,0]},"o":{"a":0,"k":100},"p":{"a":1,"k":[{"t":0,"s":[0,0],"i":{"x":0.15,"y":1.35},"o":{"x":0.15,"y":0.45},"ti":[0,0],"to":[0,0]},{"t":60,"s":[6,0],"i":{"x":0.15,"y":1.35},"o":{"x":0.15,"y":0.45},"ti":[0,0],"to":[0,0]},{"t":120,"s":[0,0],"i":{"x":0,"y":0},"o":{"x":1,"y":1}}]},"r":{"a":0,"k":0},"s":{"a":0,"k":[100,100]},"sk":{"a":0,"k":0},"sa":{"a":0,"k":0}}],"np":0},{"ty":"gr","hd":false,"nm":"Path 1 Group","bm":0,"it":[{"ty":"sh","hd":false,"nm":"Path 1","d":1,"ks":{"a":0,"k":{"c":false,"i":[[0,0],[0,0],[-7.373,-0.934],[0,0],[5.757,-0.493]],"o":[[0,0],[8.216,-0.671],[0,0],[-5.768,-0.334],[0,0]],"v":[[123.25,49.433],[119.75,24.33],[143.514,24.92],[140.559,49.194],[123.25,49.433]]}}},{"ty":"fl","hd":false,"bm":0,"c":{"a":0,"k":[0.89,0.373,0]},"r":1,"o":{"a":0,"k":100}},{"ty":"tr","nm":"Transform","a":{"a":0,"k":[0,0]},"o":{"a":0,"k":100},"p":{"a":1,"k":[{"t":0,"s":[0,0],"i":{"x":0.15,"y":1.35},"o":{"x":0.15,"y":0.45},"ti":[0,0],"to":[0,0]},{"t":60,"s":[0,-3],"i":{"x":0.15,"y":1.35},"o":{"x":0.15,"y":0.45},"ti":[0,0],"to":[0,0]},{"t":120,"s":[0,0],"i":{"x":0,"y":0},"o":{"x":1,"y":1}}]},"r":{"a":0,"k":0},"s":{"a":0,"k":[100,100]},"sk":{"a":0,"k":0},"sa":{"a":0,"k":0}}],"np":0},{"ty":"gr","hd":false,"nm":"Path 1 Group","bm":0,"it":[{"ty":"sh","hd":false,"nm":"Path 1","d":1,"ks":{"a":0,"k":{"c":false,"i":[[0,0],[0,0],[-6.332,0.775],[0,0],[3.922,-1.308]],"o":[[0,0],[5.885,-2.217],[0,0],[-8.085,1.014],[0,0]],"v":[[99.75,53.906],[97.25,29.134],[115.75,24.736],[118.25,49.958],[99.75,53.906]]}}},{"ty":"fl","hd":false,"bm":0,"c":{"a":0,"k":[1,0.667,0]},"r":1,"o":{"a":0,"k":100}},{"ty":"tr","nm":"Transform","a":{"a":0,"k":[0,0]},"o":{"a":0,"k":100},"p":{"a":1,"k":[{"t":0,"s":[0,0],"i":{"x":0.15,"y":1.35},"o":{"x":0.15,"y":0.45},"ti":[0,0],"to":[0,0]},{"t":60,"s":[-4,-1],"i":{"x":0.15,"y":1.35},"o":{"x":0.15,"y":0.45},"ti":[0,0],"to":[0,0]},{"t":120,"s":[0,0],"i":{"x":0,"y":0},"o":{"x":1,"y":1}}]},"r":{"a":0,"k":0},"s":{"a":0,"k":[100,100]},"sk":{"a":0,"k":0},"sa":{"a":0,"k":0}}],"np":0},{"ty":"gr","hd":false,"nm":"Path 1 Group","bm":0,"it":[{"ty":"sh","hd":false,"nm":"Path 1","d":1,"ks":{"a":0,"k":{"c":true,"i":[[0,0],[3,0],[0,0],[-4.667,-1.333]],"o":[[-10,-3.2],[0,0],[5.6,-0.4],[0,0]],"v":[[84.75,10.406],[63.25,6.406],[66.75,35.406],[87.75,38.906]]}}},{"ty":"fl","hd":false,"bm":0,"c":{"a":0,"k":[0.784,0.784,0.933]},"r":1,"o":{"a":0,"k":100}},{"ty":"tr","nm":"Transform","a":{"a":0,"k":[0,0]},"o":{"a":0,"k":100},"p":{"a":1,"k":[{"t":0,"s":[0,0],"i":{"x":0.15,"y":1.35},"o":{"x":0.15,"y":0.45},"ti":[0,0],"to":[0,0]},{"t":60,"s":[0,-6],"i":{"x":0.15,"y":1.35},"o":{"x":0.15,"y":0.45},"ti":[0,0],"to":[0,0]},{"t":120,"s":[0,0],"i":{"x":0,"y":0},"o":{"x":1,"y":1}}]},"r":{"a":0,"k":0},"s":{"a":0,"k":[100,100]},"sk":{"a":0,"k":0},"sa":{"a":0,"k":0}}],"np":0},{"ty":"gr","hd":false,"nm":"Path 1 Group","bm":0,"it":[{"ty":"sh","hd":false,"nm":"Path 1","d":1,"ks":{"a":0,"k":{"c":true,"i":[[0,0],[4.833,-2.833],[0,0],[-10.167,-1.166]],"o":[[-25.2,-2.4],[0,0],[12,-6.4],[0,0]],"v":[[59.25,5.906],[13.25,11.406],[16.75,38.906],[62.25,34.406]]}}},{"ty":"fl","hd":false,"bm":0,"c":{"a":0,"k":[1,0.667,0]},"r":1,"o":{"a":0,"k":100}},{"ty":"tr","nm":"Transform","a":{"a":0,"k":[0,0]},"o":{"a":0,"k":100},"p":{"a":1,"k":[{"t":0,"s":[0,0],"i":{"x":0.15,"y":1.35},"o":{"x":0.15,"y":0.45},"ti":[0,0],"to":[0,0]},{"t":60,"s":[-4,-6],"i":{"x":0.15,"y":1.35},"o":{"x":0.15,"y":0.45},"ti":[0,0],"to":[0,0]},{"t":120,"s":[0,0],"i":{"x":0,"y":0},"o":{"x":1,"y":1}}]},"r":{"a":0,"k":0},"s":{"a":0,"k":[100,100]},"sk":{"a":0,"k":0},"sa":{"a":0,"k":0}}],"np":0},{"ty":"gr","hd":false,"nm":"Path 1 Group","bm":0,"it":[{"ty":"sh","hd":false,"nm":"Path 1","d":1,"ks":{"a":0,"k":{"c":true,"i":[[0,0],[-13.208,-5.803],[0,0],[10.667,-4]],"o":[[24.5,-9.5],[0,0],[-28.8,-9.6],[0,0]],"v":[[94.75,10.906],[164.25,11.406],[164.25,24.906],[96.25,24.906]]}}},{"ty":"fl","hd":false,"bm":0,"c":{"a":0,"k":[0.784,0.784,0.933]},"r":1,"o":{"a":0,"k":100}},{"ty":"tr","nm":"Transform","a":{"a":0,"k":[0,0]},"o":{"a":0,"k":100},"p":{"a":1,"k":[{"t":0,"s":[0,0],"i":{"x":0.15,"y":1.35},"o":{"x":0.15,"y":0.45},"ti":[0,0],"to":[0,0]},{"t":60,"s":[0,-6.008],"i":{"x":0.15,"y":1.35},"o":{"x":0.15,"y":0.45},"ti":[0,0],"to":[0,0]},{"t":120,"s":[0,0],"i":{"x":0,"y":0},"o":{"x":1,"y":1}}]},"r":{"a":0,"k":0},"s":{"a":0,"k":[100,100]},"sk":{"a":0,"k":0},"sa":{"a":0,"k":0}}],"np":0},{"ty":"gr","hd":false,"nm":"Path 1 Group","bm":0,"it":[{"ty":"sh","hd":false,"nm":"Path 1","d":1,"ks":{"a":0,"k":{"c":false,"i":[[0,0],[12.833,-4.833],[0,0],[-13.167,-5.667],[-15.167,-5.833],[0,0],[0,0],[12.167,-4.833]],"o":[[-34,-11.6],[0,0],[35.6,-14.8],[27.2,-14],[0,0],[0,0],[-34,-11.6],[0,0]],"v":[[96.75,103.906],[15.75,103.906],[15.25,99.906],[99.75,98.406],[179.25,98.406],[177.75,99.906],[175.75,103.906],[96.75,103.906]]}}},{"ty":"fl","hd":false,"bm":0,"c":{"a":0,"k":[0.957,0.957,0.988]},"r":1,"o":{"a":0,"k":100}},{"ty":"tr","nm":"Transform","a":{"a":0,"k":[0,0]},"o":{"a":0,"k":100},"p":{"a":0,"k":[0,0]},"r":{"a":0,"k":0},"s":{"a":0,"k":[100,100]},"sk":{"a":0,"k":0},"sa":{"a":0,"k":0}}],"np":0},{"ty":"gr","hd":false,"nm":"Path 1 Group","bm":0,"it":[{"ty":"sh","hd":false,"nm":"Path 1","d":1,"ks":{"a":0,"k":{"c":true,"i":[[0,0],[-14,-4.833],[-15,-5.667],[0,0],[0,0],[0,0],[12.167,-4.833],[12.833,-4.833],[0,0],[0,0]],"o":[[32.4,-11.6],[27.6,-12.8],[0,0],[0,0],[0,0],[-34,-11.6],[-34,-11.6],[0,0],[0,0],[0,0]],"v":[[6.75,6.906],[89.25,6.906],[168.75,7.906],[179.25,98.406],[177.75,99.906],[175.75,103.906],[96.75,103.906],[15.75,103.906],[4.75,13.406],[6.75,11.906]]}}},{"ty":"fl","hd":false,"bm":0,"c":{"a":0,"k":[1,1,1]},"r":1,"o":{"a":0,"k":100}},{"ty":"tr","nm":"Transform","a":{"a":0,"k":[0,0]},"o":{"a":0,"k":100},"p":{"a":0,"k":[0,-0.094]},"r":{"a":0,"k":0},"s":{"a":0,"k":[100,100]},"sk":{"a":0,"k":0},"sa":{"a":0,"k":0}}],"np":0},{"ty":"gr","hd":false,"nm":"Path 1 Group","bm":0,"it":[{"ty":"sh","hd":false,"nm":"Path 1","d":1,"ks":{"a":0,"k":{"c":true,"i":[[0,0],[0,0],[0,0],[0,0],[10.833,-5.333],[11,-5.5]],"o":[[0,0],[0,0],[0,0],[-38.8,-12.8],[-40.4,-12],[0,0]],"v":[[0.75,12.906],[6.75,9.906],[177.75,100.406],[177.75,108.406],[96.75,108.406],[13.25,109.906]]}}},{"ty":"fl","hd":false,"bm":0,"c":{"a":0,"k":[0,0.525,0.71]},"r":1,"o":{"a":0,"k":100}},{"ty":"tr","nm":"Transform","a":{"a":0,"k":[0,0]},"o":{"a":0,"k":100},"p":{"a":0,"k":[0,0]},"r":{"a":0,"k":0},"s":{"a":0,"k":[100,100]},"sk":{"a":0,"k":0},"sa":{"a":0,"k":0}}],"np":0}]},{"ddd":0,"ind":14,"ty":4,"nm":"Screen","hd":false,"sr":1,"ks":{"a":{"a":0,"k":[109.5,72]},"o":{"a":0,"k":100},"p":{"a":0,"k":[109.5,72]},"r":{"a":0,"k":0},"s":{"a":0,"k":[100,100]},"sk":{"a":0,"k":0},"sa":{"a":0,"k":0}},"ao":0,"ip":0,"op":121,"st":0,"bm":0,"shapes":[{"ty":"gr","hd":false,"nm":"Screen Group","bm":0,"it":[{"ty":"rc","hd":false,"nm":"Screen","d":1,"p":{"a":0,"k":[109.5,72]},"r":{"a":0,"k":0},"s":{"a":0,"k":[219,144]}},{"ty":"fl","hd":false,"bm":0,"c":{"a":0,"k":[1,1,1]},"r":1,"o":{"a":0,"k":0}},{"ty":"tr","nm":"Transform","a":{"a":0,"k":[0,0]},"o":{"a":0,"k":100},"p":{"a":0,"k":[0,0]},"r":{"a":0,"k":0},"s":{"a":0,"k":[100,100]},"sk":{"a":0,"k":0},"sa":{"a":0,"k":0}}],"np":0}]}],"meta":{"g":"@phase-software/lottie-exporter 0.6.0"},"nm":"","op":120,"v":"5.6.0","w":219}